JavaKaiyuanXiangmuZhongwenWendang/README.md
JavaKaiyuanXiangmuZhongwenWendang/__init__.py
JavaKaiyuanXiangmuZhongwenWendang/__main__.py
JavaKaiyuanXiangmuZhongwenWendang/file.epub
JavaKaiyuanXiangmuZhongwenWendang/index.html
JavaKaiyuanXiangmuZhongwenWendang/css/__init__.py
JavaKaiyuanXiangmuZhongwenWendang/css/annotations.css
JavaKaiyuanXiangmuZhongwenWendang/css/main.css
JavaKaiyuanXiangmuZhongwenWendang/css/normalize.css
JavaKaiyuanXiangmuZhongwenWendang/css/popup.css
JavaKaiyuanXiangmuZhongwenWendang/font/__init__.py
JavaKaiyuanXiangmuZhongwenWendang/font/fontello.eot
JavaKaiyuanXiangmuZhongwenWendang/font/fontello.svg
JavaKaiyuanXiangmuZhongwenWendang/font/fontello.ttf
JavaKaiyuanXiangmuZhongwenWendang/font/fontello.woff
JavaKaiyuanXiangmuZhongwenWendang/img/__init__.py
JavaKaiyuanXiangmuZhongwenWendang/img/annotator-glyph-sprite.png
JavaKaiyuanXiangmuZhongwenWendang/img/annotator-icon-sprite.png
JavaKaiyuanXiangmuZhongwenWendang/img/apple-touch-icon.png
JavaKaiyuanXiangmuZhongwenWendang/img/cancelfullscreen.png
JavaKaiyuanXiangmuZhongwenWendang/img/close.png
JavaKaiyuanXiangmuZhongwenWendang/img/fullscreen.png
JavaKaiyuanXiangmuZhongwenWendang/img/loader.gif
JavaKaiyuanXiangmuZhongwenWendang/img/menu-icon.png
JavaKaiyuanXiangmuZhongwenWendang/img/save.png
JavaKaiyuanXiangmuZhongwenWendang/img/saved.png
JavaKaiyuanXiangmuZhongwenWendang/img/settings-s.png
JavaKaiyuanXiangmuZhongwenWendang/img/settings.png
JavaKaiyuanXiangmuZhongwenWendang/img/star.png
JavaKaiyuanXiangmuZhongwenWendang/js/__init__.py
JavaKaiyuanXiangmuZhongwenWendang/js/epub.js
JavaKaiyuanXiangmuZhongwenWendang/js/epub.min.js
JavaKaiyuanXiangmuZhongwenWendang/js/epub.min.map
JavaKaiyuanXiangmuZhongwenWendang/js/hooks.min.js
JavaKaiyuanXiangmuZhongwenWendang/js/hooks.min.map
JavaKaiyuanXiangmuZhongwenWendang/js/reader.js
JavaKaiyuanXiangmuZhongwenWendang/js/reader.js.map
JavaKaiyuanXiangmuZhongwenWendang/js/reader.min.js
JavaKaiyuanXiangmuZhongwenWendang/js/reader.min.map
java_kaiyuan_xiangmu_zhongwen_wendang-2024.3.1.0.dist-info/METADATA
java_kaiyuan_xiangmu_zhongwen_wendang-2024.3.1.0.dist-info/WHEEL
java_kaiyuan_xiangmu_zhongwen_wendang-2024.3.1.0.dist-info/entry_points.txt
java_kaiyuan_xiangmu_zhongwen_wendang-2024.3.1.0.dist-info/top_level.txt
java_kaiyuan_xiangmu_zhongwen_wendang-2024.3.1.0.dist-info/RECORD
